retools/__init__.py
retools/cache.py
retools/event.py
retools/exc.py
retools/jobs.py
retools/limiter.py
retools/lock.py
retools/queue.py
retools/util.py
retools/tests/__init__.py
retools/tests/jobs.py
retools/tests/test_cache.py
retools/tests/test_limiter.py
retools/tests/test_lock.py
retools/tests/test_queue.py
retools/tests/test_util.py
retools-0.4.1.data/scripts/retools-worker
retools-0.4.1.dist-info/DESCRIPTION.rst
retools-0.4.1.dist-info/entry_points.txt
retools-0.4.1.dist-info/METADATA
retools-0.4.1.dist-info/pydist.json
retools-0.4.1.dist-info/RECORD
retools-0.4.1.dist-info/top_level.txt
retools-0.4.1.dist-info/WHEEL
