Metadata-Version: 1.1
Name: retools
Version: 0.4.1
Summary: Redis Tools
Home-page: http://readthedocs.org/docs/retools/
Author: Ben Bangert
Author-email: ben@groovie.org
License: MIT
Keywords: cache redis queue lock
Platform: UNKNOWN
Classifier: Intended Audience :: Developers
Classifier: Programming Language :: Python
